aifunc/__init__.py
aifunc/add_ai_function.py
aifunc/evaluate_answer.py
aifunc/follow_up.py
aifunc/generate_question.py
aifunc/utility.py
aifunc-0.5.8.dist-info/METADATA
aifunc-0.5.8.dist-info/WHEEL
aifunc-0.5.8.dist-info/RECORD
