Metadata-Version: 2.1
Name: aifunc
Version: 0.5.8
Summary: 
Author: Ziyan Wu
Author-email: ziyanwu93@gmail.com
Requires-Python: >=3.10,<4.0
Classifier: Programming Language :: Python :: 3
Classifier: Programming Language :: Python :: 3.10
Classifier: Programming Language :: Python :: 3.11
Requires-Dist: openai (>=0.27.8,<0.28.0)
Requires-Dist: pyyaml (>=6.0,<7.0)
Requires-Dist: urllib3 (>=1.26,<2.0)
